plone.schema-2.0.3-py3.13-nspkg.pth
plone/schema/__init__.py
plone/schema/configure.zcml
plone/schema/editor.py
plone/schema/email.py
plone/schema/handler.py
plone/schema/interfaces.py
plone/schema/jsonfield.py
plone/schema/path.py
plone/schema/browser/__init__.py
plone/schema/browser/configure.zcml
plone/schema/browser/email.py
plone/schema/browser/jsonfield.py
plone/schema/browser/uri.py
plone/schema/browser/templates/email_display.pt
plone/schema/browser/templates/uri_display.pt
plone/schema/tests/__init__.py
plone/schema/tests/test_email.py
plone/schema/tests/test_jsonfield.py
plone_schema-2.0.3.dist-info/METADATA
plone_schema-2.0.3.dist-info/WHEEL
plone_schema-2.0.3.dist-info/namespace_packages.txt
plone_schema-2.0.3.dist-info/top_level.txt
plone_schema-2.0.3.dist-info/RECORD
