Metadata-Version: 2.4
Name: plone.schema
Version: 2.0.3
Summary: Plone specific extensions and fields for zope schematas
Home-page: https://github.com/plone/plone.schema
Author: Plone Foundation
Author-email: plone-developers@lists.sourceforge.net
License: BSD
Keywords: schema z3cform email uri json field widget
Classifier: Development Status :: 5 - Production/Stable
Classifier: Framework :: Zope :: 5
Classifier: Framework :: Plone
Classifier: Framework :: Plone :: 6.0
Classifier: Framework :: Plone :: 6.1
Classifier: Framework :: Plone :: Core
Classifier: Programming Language :: Python
Classifier: Programming Language :: Python :: 3.8
Classifier: Programming Language :: Python :: 3.9
Classifier: Programming Language :: Python :: 3.10
Classifier: Programming Language :: Python :: 3.11
Classifier: Programming Language :: Python :: 3.12
Classifier: Programming Language :: Python :: 3.13
Classifier: Topic :: Software Development :: Libraries :: Python Modules
Classifier: License :: OSI Approved :: BSD License
Requires-Python: >=3.8
Requires-Dist: jsonschema
Requires-Dist: setuptools
Requires-Dist: z3c.form
Requires-Dist: zope.i18nmessageid
Requires-Dist: zope.interface
Requires-Dist: zope.component
Requires-Dist: zope.schema
Provides-Extra: test
Provides-Extra: schemaeditor
Requires-Dist: plone.schemaeditor; extra == "schemaeditor"
Provides-Extra: supermodel
Requires-Dist: plone.supermodel; extra == "supermodel"
Dynamic: author
Dynamic: author-email
Dynamic: classifier
Dynamic: description
Dynamic: description-content-type
Dynamic: home-page
Dynamic: keywords
Dynamic: license
Dynamic: provides-extra
Dynamic: requires-dist
Dynamic: requires-python
Dynamic: summary
